vertex_batch/__init__.py
vertex_batch/callback.py
vertex_batch/db.py
vertex_batch/file.py
vertex_batch/line.py
vertex_batch-1.0.3.dist-info/METADATA
vertex_batch-1.0.3.dist-info/WHEEL
vertex_batch-1.0.3.dist-info/top_level.txt
vertex_batch-1.0.3.dist-info/RECORD
